bye_bye_shopify/__init__.py
bye_bye_shopify/cli.py
bye_bye_shopify/client.py
bye_bye_shopify/config.py
bye_bye_shopify/loaders.py
bye_bye_shopify/models.py
bye_bye_shopify-0.0.1.dist-info/METADATA
bye_bye_shopify-0.0.1.dist-info/WHEEL
bye_bye_shopify-0.0.1.dist-info/entry_points.txt
bye_bye_shopify-0.0.1.dist-info/top_level.txt
bye_bye_shopify-0.0.1.dist-info/RECORD
