Metadata-Version: 2.1
Name: bye-bye-shopify
Version: 0.0.1
Summary: Extract product catalogue (including images) from your Shopify store to JSON files
Home-page: https://github.com/jbasko/bye-bye-shopify
Author: Jazeps Basko
Author-email: jazeps.basko@gmail.com
Maintainer: Jazeps Basko
Maintainer-email: jazeps.basko@gmail.com
License: MIT
Keywords: shopify extract export products images json
Platform: UNKNOWN
Classifier: Development Status :: 4 - Beta
Classifier: Intended Audience :: Developers
Classifier: Topic :: Software Development :: Libraries
Classifier: Programming Language :: Python
Classifier: Programming Language :: Python :: 3
Classifier: Programming Language :: Python :: 3.6
Classifier: License :: OSI Approved :: MIT License
Requires-Python: >=3.6.0
Requires-Dist: aarghparse (>=0.2.0)
Requires-Dist: requests
Requires-Dist: strictus-dictus (>=0.0.12)
Requires-Dist: wr-profiles
